<?xml version="1.0" encoding="UTF-8" standalone="no"?>
<pk><wd nm="pecifying" rd="9,0:1139|12,0:773,2468,2494|16,0:2229|18,0:1021,4536|19,0:3411|20,0:773,1565|27,0:1175|31,0:21640|35,0:192|37,0:8448|48,0:2179|54,0:16442|60,0:15209|68,0:18017|75,0:271,313|88,0:19238,23845|89,0:19604,22859|90,0:23775|91,0:27209|92,0:19523,24129|93,0:19821,23074|94,0:1413,8158|97,0:2849,4448,4842,5038,6171,6296,6421|105,0:3880|112,0:672|113,0:4363|115,0:4174|116,0:398|117,0:8736|119,0:643|126,0:277|167,0:13644|169,0:1644,2190,2408,2551|172,0:4773,5040,5463|173,0:6663|182,0:13812,20168,24711|192,0:1231,34148|196,0:8515|197,0:11392,11953|205,0:2161,3763,4157,4353,5485,5610,5735|217,0:2736|219,0:19192|224,0:19328|225,0:3051|226,0:2976|232,0:1182|235,0:20559|239,0:3520|245,0:13248|246,0:6748|249,0:240,712|251,0:12769|253,0:303,1066|255,0:15566|257,0:776|259,0:8317|260,0:8800|275,0:18167"/><wd nm="pect" rd="0,0:2774|33,0:6001,6396,8310,17407|66,0:466|87,0:140|88,0:4972,42706|89,0:4421,39278|90,0:4914,8063,40316,43437,44003|91,0:4893,8043,44032,47153,47719|92,0:5124,42993|93,0:4436,39480|105,0:12335|126,0:1741|138,0:492|141,0:1611|162,0:3716|164,0:894|166,0:269|182,0:32770|192,0:7359,7456,11252,12169,33366,34706,34778|207,0:5745,12358|243,0:200|251,0:17331|255,0:19157"/><wd nm="pection" rd="174,0:1153,2631|176,0:6549,7924"/><wd nm="pective" rd="1,0:3083|11,0:1416|12,0:1952|14,0:2657,2875|32,0:3304|33,0:10998|34,0:3580|37,0:7121|40,0:6008|41,0:3929|46,0:8601|68,0:9676|69,0:3366,3584|73,0:133|82,0:3558|96,0:3082|117,0:4473|135,0:940,1450|141,0:441|150,0:2709|155,0:288|161,0:226|162,0:2358|167,0:9956|169,0:325|182,0:6422,13062|186,0:243|187,0:1945|189,0:815|192,0:13205,23151,30755|200,0:1164|202,0:1972|214,0:9977|241,0:2563|245,0:9596|260,0:1756,5058,5363|265,0:6733"/><wd nm="pectively" rd="11,0:1477,3219,3293|18,0:457|19,0:390,730|33,0:2540|48,0:342|55,0:480|61,0:421|62,0:612|70,0:587|90,0:37893|91,0:41436|115,0:2431|143,0:2424|146,0:7641|163,0:2345|169,0:736|192,0:10750|197,0:20036|207,0:12997,18846,29287|216,0:405|217,0:687,919|225,0:558|226,0:394,734|228,0:735|242,0:1405|260,0:3427|268,0:430|269,0:315"/><wd nm="pects" rd="18,0:4104|20,0:83|47,0:78,228|105,0:7542|109,0:1605|111,0:1788|130,0:121|192,0:19984,23043|207,0:2634|209,0:1009|237,0:100|250,0:1513|254,0:2485|258,0:1320|265,0:3292"/><wd nm="ped" rd="17,0:5070,5232|23,0:1118|24,0:562|33,0:13272|44,0:1237,1334,1524,3837,3944|46,0:9972,10066|50,0:714|51,0:559|58,0:561|64,0:722|65,0:563|71,0:128|73,0:505|77,0:746|80,0:588|106,0:3621|108,0:1700|127,0:463,5991|133,0:4076,6744|146,0:8452|165,0:561|173,0:560|176,0:9019,9150|182,0:19944|192,0:1420,35306|203,0:4249|220,0:713|221,0:558|229,0:1168|230,0:571|244,0:562|252,0:560|267,0:1321|271,0:728|272,0:566"/><wd nm="peed" rd="260,0:8945"/><wd nm="peeding" rd="260,0:9689,9797"/><wd nm="peedometer" rd="26,0:75|146,0:356,2083"/><wd nm="peexception" rd="97,0:8628|196,0:2582,3271"/><wd nm="peg" rd="0,0:172|31,0:21133|36,0:1489|37,0:239,457|46,0:7761|54,0:15935|60,0:14702|68,0:17510|88,0:23337|89,0:22351|90,0:23267|91,0:26701|92,0:23621|93,0:22567|94,0:2496,9241|119,0:4808|122,0:238|124,0:642|126,0:114,2874|128,0:5828,8702|130,0:367|135,0:2391|136,0:238|145,0:119,2093,3721|167,0:13135|182,0:13305|219,0:18684|224,0:18821|235,0:20052|245,0:12740|251,0:12261|255,0:15058|259,0:7810|275,0:17659"/><wd nm="peline" rd="164,0:119"/><wd nm="pelinks" rd="94,0:1972,8717|101,0:1449,1541|107,0:2833,2925|108,0:4393,4485|109,0:4319,4411"/><wd nm="pelling" rd="265,0:7717"/><wd nm="pen" rd="1,0:937|9,0:1733,1830|27,0:3238,5405|31,0:6543,10564|53,0:2334,4238|54,0:5321,6457|60,0:4261|67,0:2338,4242|68,0:5094,8904|71,0:2097|88,0:7688,12103,40856|89,0:6990,12118,37964|90,0:7629,12555,41629|91,0:1584,1665,2398,2482,7609,13669,45345|92,0:7839,12443,41142|93,0:6993,12401,38167|96,0:2794,5245|98,0:342|102,0:58,220,387,485,2757|105,0:2824,7389,7466|107,0:1291|108,0:86,116,471,552,2281|109,0:535,856,889,913,944,2917,2983,3121|111,0:1432|113,0:2487,2549|123,0:3359|130,0:1546,1608|132,0:2184,2243|135,0:2968|138,0:287,2156,3342,6321,7222|140,0:2840|144,0:264,391,806,842,878,919,2713|146,0:4033,8709,11926|148,0:1106|149,0:4990,6000,7685|153,0:2495,4932|167,0:3912,20179|182,0:8608|190,0:4620|196,0:13468|198,0:3461|207,0:2706,2766,2805,2849,2893,13249,13750,13877,13924,15262,15307,17625,18174,18221,19099,19599,19727,19774,21112,21157,23014,23147,23192,24762,26750,26948,28626,30438,30565|210,0:5679|213,0:8740|219,0:5714,9497|223,0:2331,4235|224,0:5887,9693|232,0:3267,5443|235,0:6569,10466|245,0:4054,19801|251,0:4632|253,0:166,1239,1323,1411,1532,1766,2111|255,0:192,6046,11085,11146,11262|256,0:863,922,965|259,0:3758|274,0:2344,4300|275,0:5211,8888"/><wd nm="penanchor" rd="253,0:1906,1990|255,0:11579"/><wd nm="pencolor" rd="253,0:1589,1673|255,0:11398"/><wd nm="pend" rd="20,0:3054|71,0:765|86,0:1721,1966|95,0:1347|105,0:1073|135,0:1091|138,0:1864|146,0:11411|149,0:1302|163,0:2509|192,0:21975|207,0:1086|246,0:257|248,0:1636,1881"/><wd nm="pended" rd="105,0:7321|212,0:440"/><wd nm="pendencies" rd="135,0:1254|177,0:297|184,0:634"/><wd nm="pendency" rd="138,0:5284"/><wd nm="pendent" rd="24,0:255|51,0:252|58,0:254|65,0:256|80,0:281|127,0:1531|133,0:246|138,0:9322|147,0:738|164,0:1459|165,0:254|173,0:253|195,0:5675|197,0:19050,21725,23747|221,0:251|230,0:264|244,0:255|252,0:253|265,0:4024|272,0:259"/><wd nm="pendently" rd="190,0:213"/><wd nm="pendfusioncharts" rd="152,0:8537,8687,8895,8952,9121,9145|192,0:26345,26495,26735,26792|210,0:453,544,6164,6356,6516,6677,6808,7030,7120,7283,7444,7576|211,0:3021,3726,4314|213,0:9347,9404"/><wd nm="pending" rd="5,0:2103|8,0:504|14,0:2406|69,0:3086|80,0:4741|94,0:1077|97,0:1037|113,0:1010|115,0:9569|125,0:1905|127,0:1896|137,0:1197|138,0:2087|141,0:801|143,0:1688|147,0:3178,4837|152,0:8361,8377|161,0:2799,10494|167,0:10030|187,0:137,2616|210,0:3071,9891|211,0:1797|213,0:4585|214,0:3394|245,0:9671|260,0:4204|265,0:2051"/><wd nm="pends" rd="27,0:466|53,0:469|67,0:473|74,0:111|119,0:5373|128,0:7418,8273|135,0:3236|138,0:9510|161,0:5729,9488|209,0:4180|223,0:466|232,0:464|246,0:715,5928|260,0:5546|274,0:479"/><wd nm="pened" rd="102,0:575|105,0:518,1875|108,0:371|140,0:2958|143,0:534|146,0:9678|149,0:516,7504|192,0:21754|196,0:13539,13761,13827,14103,14459|198,0:3482|207,0:530,1994"/><wd nm="pening" rd="71,0:1256|74,0:3213|87,0:1072,1600,1848|95,0:1850|96,0:122|101,0:386,416,458|105,0:7599,14126|108,128:0,29,4603|109,0:2868|128,0:6592|146,0:11766|154,0:415,519|207,0:7493,13936,17014,19786,23272,27127|246,0:3825|253,0:2373|255,0:2944,11426,11629,11991"/><wd nm="penings" rd="163,0:2311"/><wd nm="pens" rd="3,0:784|97,0:3176|101,0:179|104,0:3047,4079|105,0:4834|106,0:3955|107,0:779,978,1186,1436|125,0:1286|127,0:2618,5802|141,0:2619|146,0:5958|149,0:5792,6897,6935|150,0:2829|152,0:5652|196,0:3625|205,0:2488|213,0:5776"/><wd nm="pensechart" rd="113,0:2098|132,0:1776"/><wd nm="pensive" rd="190,0:3505"/><wd nm="pentagon" rd="41,0:3373|46,0:8391"/><wd nm="penvalue" rd="253,0:2215,2282|255,0:2920,11948"/><wd nm="peof" rd="126,0:3330,4392"/><wd nm="people" rd="163,0:423"/><wd nm="per" rd="1,0:1072|5,0:1427,2961|7,0:4463|16,0:4530|19,0:331,2120,2268,3561|22,0:444,1065|26,0:632,1082|27,0:5380|28,0:1769,2779|31,0:2317,7395,7476,8119,8155,8270,8479,15950|33,0:6179,17585|37,0:7933|40,0:10347|42,0:2787|48,0:283,1528,2308|49,0:595|52,0:989|53,0:4213|54,0:7876,7957,10734|56,0:232|57,0:4547,4802,4912,5210,5478,7436|60,0:5048,5129,5413,5711,5972,7872|62,0:433,568,1223|66,0:651|67,0:4217|68,0:1423,5946,6201,6670,6706,6821,7030,8025,12309|70,0:232,1337,1601,2107|71,0:641,2072|72,0:9771|88,0:9488,12629,14111|89,0:9349,12644,14126|90,0:8294,9940,13081,14563,40572,43662|91,0:8274,10321,10681,14195,15677,19132,44288,47378|92,0:9658,12969,14451|93,0:9367,12927,14408|95,0:1223|97,0:205,3023,8175|98,0:317|105,0:4864,8598|107,0:2457|117,0:992,1557,1579,1596,1874|131,0:1672|138,0:1186,3609,6122|139,0:1527|141,0:2504,4526|143,0:2057|146,0:5788,5826,7559,7772|149,0:2368,5300,6302,7655|150,0:4645,5132|151,0:571,598,855,1022,1050|161,0:10310|167,0:6662,10073,17382|176,0:878,3191,5014|183,0:2240,2267,2397,2567,2595|184,0:2030,2057,2187,2354,2382|190,0:4788|191,0:176|192,0:7250,7752,11430,12347|196,0:1257,7787|197,0:13896|201,0:3605,4004|202,0:978|203,0:3224,3623|205,0:1122,1514,2335|206,0:5602|207,0:8487|208,0:2977|209,0:360|215,0:2483|217,0:625,1826,1974,2865|218,0:568|219,0:2016,6565,6646,7291,7327,7442,7651,8619,13500|222,0:1075|223,0:4210|224,0:2192,6739,7459,7495,7610,7819,8814,13638|226,0:335,2072,2220,3105|228,0:631,931|231,0:1393|232,0:5418|235,0:2243,7421,7502,8144,8180,8295,8504,14869|245,0:6591,9715,16993|251,0:3171,3262,6359|255,0:4585,4676,7520|260,0:7578|263,0:3549|265,0:5550|269,0:261,1016|273,0:560|274,0:4275|275,0:1422,6062,6143,6788,6824,6939,7148,12464"/><wd nm="per:visible" rd="211,0:8534|215,0:2315"/><wd nm="pera" rd="146,0:4113|192,0:842,19470"/><wd nm="perating" rd="71,0:807|95,0:1389|139,0:719,786|236,0:2299|239,0:2063,2358"/><wd nm="peration" rd="127,0:6016|133,0:7172|202,0:637|222,0:546|260,0:8772"/><wd nm="perative" rd="33,0:5873|192,0:11124"/><wd nm="perators" rd="40,0:11604"/><wd nm="perature" rd="13,0:252,297|14,0:2762|15,0:186,231|69,0:194,239,3471|239,0:2947,4159,4437,4826|247,0:1344,1715,1795|269,0:116"/><wd nm="peratures" rd="273,0:93"/><wd nm="percent" rd="11,0:4994,5048,5086,5861,5961|16,0:1267|31,0:11990,13766,13792,13832,13948,13974,14015,23597|54,0:8488,8514,8554,8670,8696,8737,18391|55,0:1723,1743,1777,1797|57,0:10415,10451,10505,10543,15903|60,0:10865,10900,10954,10991,17156|68,0:10063,10089,10129,10245,10271,10312,19970|88,0:17192,17218,17258,17374,17400,17441,32642|89,0:17207,17233,17273,17389,17415,17456,30907,32388,32412,32690,32753|90,0:17644,17670,17710,17826,17852,17893,32662|91,0:20975,21001,21041,21157,21183,21224,36206|92,0:8122,17477,17503,17543,17659,17685,17726,32925|93,0:7831,17425,17451,17491,17607,17633,17674,31115,32596,32620,32898,32961|141,0:1489|162,0:3685|163,0:1543|167,0:17982,18648|169,0:6492,6555|177,0:1875|178,0:3830,3893|179,0:212,411,816,1286,1328,1501|182,0:5887,5962,6115,6220,6804,6961,12430,20354,23248,24724,25374,25430,25472,25533,25647,28851,28896|195,0:4330|200,0:4944,5366|219,0:11259,11285,11325,11441,11467,11508,21148|224,0:11454,11480,11520,11636,11662,11703,21281|235,0:12629,12655,12695,12811,12837,12878,22506|240,0:1370,1434,1550,1615|245,0:17594,18261|251,0:15456,15875,15899,16121,16184|255,0:17522|259,0:10270,10759,10783,11005,11068|275,0:10279,10305,10345,10461,10487,10528,20123"/></pk>