<?xml version="1.0" encoding="UTF-8" standalone="no"?>
<pk><wd nm="talabels" rd="0,0:1142,1825|11,0:1785,2040,2809,3064|88,0:3731|89,0:3468|90,0:3673|91,0:3652|92,0:3883|93,0:3495|96,0:1279|167,0:1756|245,0:1891"/><wd nm="taled" rd="164,0:816|166,0:149"/><wd nm="talic" rd="37,0:2673,4191|44,0:988,3399|46,0:9534|169,0:1829,1963,2323,2395,2640,2776,2987,3063|182,0:18449,18492,19641,19691,20829,21663,22589,26528,27513,28303,29285,30124|263,0:642,1267,2332,2507,2619,2714,2721,2743,2753"/><wd nm="talicized" rd="44,0:950,3440|46,0:9575|263,0:2879"/><wd nm="talics" rd="31,0:22209|44,0:912|54,0:16997|57,0:14575|60,0:15768|68,0:18576|88,0:27751|89,0:26017|90,0:27772|91,0:31315|92,0:28034|93,0:26227|167,0:14203|182,0:20891,21712,22641,26583,27554,28358,29326,30165|219,0:19752|224,0:19887|235,0:21118|245,0:13808|251,0:14066|255,0:16126|259,0:8876|263,0:682|275,0:18727"/><wd nm="taligncaption" rd="192,0:33631,33782,33907,34048"/><wd nm="talignsubcaption" rd="192,0:33683,33834,33957,34098"/><wd nm="talked" rd="37,0:7640"/><wd nm="tall" rd="133,0:7353|139,0:834|161,0:1602|190,0:1471"/><wd nm="tallation" rd="152,0:5473|188,0:52,219,622,2474,2696|197,0:7431|210,0:3994,10817|211,0:2718|213,0:5507|214,0:4321|236,0:2343|239,0:2107,2402"/><wd nm="talled" rd="94,0:6864|126,0:4645|128,0:2311,2379|129,0:1061,1210,2176|133,0:3379|135,0:1147,1266|146,0:5098|153,0:261|189,0:185,849|190,0:3691|191,0:400,767|192,0:4190,4403"/><wd nm="talling" rd="188,128:0,25,171,719,2923"/><wd nm="tallredirect" rd="152,0:5382|197,0:7340|210,0:3903,10726|211,0:2628|213,0:5416|214,0:4229"/><wd nm="tally" rd="0,0:2733|31,0:20903|36,0:739|44,0:1773|54,0:15705|57,0:14026|59,0:541|60,0:14472|68,0:17280|88,0:23107|89,0:22121|90,0:23037|91,0:26471|92,0:23391|93,0:22337|125,0:2010|167,0:12905|172,0:197|182,0:11089|217,0:182|219,0:18454|222,0:428|224,0:18591|235,0:19822|245,0:12510|251,0:12031|255,0:14828|259,0:7580|262,0:267|275,0:17429"/><wd nm="taload" rd="196,0:5417"/><wd nm="taloadcancelled" rd="196,0:5488|197,0:3888,10469|198,0:3333"/><wd nm="taloaded" rd="196,0:7299,7310,7463|197,0:3729,3742,10310,10323|198,0:3387,3752|208,0:1825"/><wd nm="taloaderror" rd="97,0:6741|196,0:14754,14768,14947|197,0:3942,3956,10523,10537|198,0:3603,3808|205,0:790,1362|208,0:1880"/><wd nm="taloadrequest" rd="196,0:4267,4442"/><wd nm="taloadrequestcancelled" rd="196,0:4345|197,0:3863,10444|198,0:3283"/><wd nm="taloadrequestcompleted" rd="196,0:4940|197,0:3672,10253|198,0:3308"/><wd nm="taloadrequested" rd="196,0:3835,4475|197,0:3654,10235|198,0:3265"/><wd nm="talpha" rd="261,0:794"/><wd nm="tamenuitem" rd="110,0:980|111,0:575,818,1040"/><wd nm="tamenuitemlabel" rd="111,0:1221,1294"/><wd nm="tamp" rd="9,0:691,835,938,1296,1800,2247,2291,2681,2752,4074,4164|27,0:3325,3364,3470|31,0:10651,10690,10796|53,0:2421,2460,2566|54,0:6544,6583,6689|67,0:2425,2464,2570|68,0:8991,9030,9136|86,128:31,48,1130,1139,1430,1590,1741,1804,1912,1986,2089,2216,2305,2363,2493,2530,2667,2819,3041,3140,3288,3409,3438,3527,3709|88,0:12806,12845,12951|89,0:12821,12860,12966|90,0:13258,13297,13403|91,0:14372,14411,14517|92,0:13146,13185,13291|93,0:13104,13143,13249|94,0:7588,7882,7968|138,0:1877,3090,3289,3308,4805,5025,5054,7092,7195,8149,8316,8352,9624|195,0:2781,2796|219,0:9584,9623,9729|223,0:2418,2457,2563|224,0:9780,9819,9925|232,0:3354,3393,3500|235,0:10553,10592,10698|248,128:32,49,1045,1054,1345,1505,1656,1719,1827,1901,2004,2118,2173,2303,2340,2485,2637,2859,2958,3106,3227,3256,3348,3531|274,0:2431,2470,2576|275,0:8975,9014,9120"/><wd nm="tance" rd="0,0:1061,1751|1,0:1370|7,0:5021,5065,5098|17,0:1215,2590,3231,4218|19,0:1337,1705,2685,2864|21,0:1407,1966|23,0:3189|24,0:2058|27,0:3610,4230|28,0:413,1132|29,0:248,2181,2215|30,0:2940|31,0:646,1014,9249,9282,9320,9354|33,0:14645,15855|35,0:496,753|37,0:1616,3228,8115|40,0:1225,3287,4335|43,0:512,769|44,0:4199,5348|45,0:1052,2448|54,0:19179|57,0:6048,6080,6116,6149,16350|60,0:6540,6572,6608,6641,17600|61,0:2744,2919|68,0:7798,7830,7866,7899,20758|72,0:10237|87,0:273|88,0:33351,33508,34257|89,0:31523,31680,32831|90,0:33371,33528,34280|91,0:36915,37072,37824|92,0:33634,33791,34543|93,0:31731,31888,33039|99,0:3185,6440,7864|105,0:12417|108,0:1962,2110|115,0:599,2499,2542,3029,3545,3856,4008,5426|117,0:227,396,456,468,607,667,984,1849,2472,4496,4719,4864,5017,7640|119,0:544,616,728,771,1258,1777,2160,2309,2478,8845|120,0:188,2469|127,0:529|128,0:4506,4690|129,0:2022|133,0:4159|145,0:616|152,0:2193|155,0:941,1225|157,0:735|158,0:443|159,0:654|160,0:1754,4376|161,0:4293,7861|167,0:4898,4950|192,0:20728|196,0:3515,3571,14073,14429|197,0:638,3442,6034,8850,18563,18711,22166,23597,24044,24537|198,0:1812|199,0:709,1122,1462,2347,2514,2972,3430|207,0:5827,12440|208,0:2015|209,0:2673|219,0:8389,8421,8460,8493,10528,21936|224,0:8587,8619,8655,8688,10724,22069|233,0:2278,2299,2331,2351|234,0:2309|235,0:9330,9362,9403,9436,9474,9508,23294|245,0:5042,5094|259,0:10727|261,0:318,336,2080,2114,2191,2258,2298,2307,2334,2588,2689|266,0:234,252,1253,1304,1373,1442,1491,1500,1525,1793,1977,2068,2408,2497,2827,2908,3191,3272|267,0:2600|268,0:2851,3026|275,0:7826,7858,7899,7932,20911"/><wd nm="tances" rd="117,0:956,4132|133,0:6794|160,0:302,4131|192,0:14560|198,0:1338|199,0:477|200,0:1039|208,0:662"/><wd nm="tand" rd="8,0:182|24,0:190|51,0:187|58,0:189|65,0:191|80,0:216|119,0:5526|146,0:4593|154,0:198|161,0:7168|165,0:189|173,0:188|184,0:288|190,0:1546|221,0:186|230,0:199|244,0:190|252,0:188|272,0:194"/><wd nm="tandard" rd="6,0:1096,1659|7,0:5083|9,0:1370|22,0:280|63,0:204|103,0:409|105,0:12153|123,0:1031|128,0:5356|168,0:406|199,0:2264|203,0:2896|206,0:811,3078,3350|207,0:5561,12174|218,0:228|228,0:265|270,0:229"/><wd nm="tanding" rd="16,0:1360|69,0:620|81,0:597|104,0:492|106,0:489|152,0:517|210,0:651|212,0:495|213,0:698|214,0:906|215,0:523"/><wd nm="taneous" rd="168,0:3126|260,0:2782"/><wd nm="tangle" rd="16,0:496,1633,1782,1832,2075,2125,2474,2517,2565,2605,2650,2692,2741,2783,2871,3058,3093,3132,3166,3204,3240,3280,3318,3358,3395,3435,3472,3512,3549,3589,3625,3664,3700,4056,4107|17,0:2479,3114|19,0:1280,1644,2324,2620,2803|21,0:1350,1905|23,0:3129|24,0:1993|27,0:3553,4169|28,0:356,1071|31,0:589,953,11099,26335|32,0:656,694,1643,1920,2155,3118,3271,3395,5366,5649|33,0:353,1476,2147,2378,2868,2947,3253,11275,11512,14395,15590|34,0:2490,3394,3547,3670|35,0:362,650|36,0:899,958,976,2021,2127,2504,2593|37,0:339,1366,2963,4814,5258,5779,6325,11802,11990|39,0:1308,2717,3705|40,0:995,3057,4077,9269,10646,10726,10789,10958,11154,11275,11362,11456,11552|41,0:1740,1768,2261,2485,2677,3743,3896,4019|42,128:11,22,52,127,192,273,408,529,622,695,849,1002,1939,2021,2365,2582,2744,2852,2911,2929,3460,3604,3754,3804,5438,5878,5984,6215,6304,6542|43,0:130,172,261,378,666,1191,1529,1851,2185|44,0:2065,2137,4346,5491|45,0:995,2387|46,0:5799,6738,6883,7112,7260,8415,8568,8691,10174,10254|88,0:43946|89,0:40518|90,0:45243|91,0:49073|92,0:44233|93,0:40720|99,0:397,479,562,4190,4256,4323|152,0:2136|157,0:670|160,0:1689|161,0:4228|162,0:1194,1671,3280,3311|163,0:2555,2589|165,0:2001|167,0:540,841,9815|182,0:32075|192,0:10361,10588|251,0:18198|255,0:20024"/><wd nm="tangles" rd="37,0:153|99,0:345,680,3141,3229,4148,4419,6382,6481,7806,7905"/><wd nm="tanimation" rd="31,0:3255|54,0:1939|57,0:2725|60,0:2692|68,0:1920|88,0:6035|89,0:5484|90,0:5977|91,0:5956|92,0:6187|93,0:5487|167,0:2343|182,0:7290|219,0:2516|224,0:2689|235,0:3174|245,0:2485|251,0:2482|255,0:3749|259,0:2136|275,0:1922"/><wd nm="tanimationstyle" rd="265,0:328,572,795,1007,1748,2630,2777,3627,3774,6258,6437"/><wd nm="tank" rd="231,0:1257"/><wd nm="tanker" rd="39,0:3266,4146|44,0:4895,5932|62,0:143,550|140,0:771,824,947,2122"/><wd nm="tanker_thermometer" rd="140,0:2148"/><wd nm="tant" rd="16,0:3772|24,0:3448|27,0:6248|33,0:5687|37,0:11607|40,0:1306,1389,1439,1500,1527,1551,1607,1626,1709,1771,1824,1845,1869,1931,2053,2074,11778|51,0:3029|53,0:5081|58,0:3286|65,0:2610|67,0:5085|70,0:4891|71,0:2940|80,0:5754|96,0:630|98,0:1185|105,0:7845|115,0:2838|119,0:1067|120,0:613|123,0:233|138,0:2299,2455,2531,2545,2677,3397,3559,4204,4218,4356,6591,6723,7306,7462,7575,7707|141,0:433|146,0:9323|147,0:4809|152,0:3061,6904|154,0:1263|165,0:3435|168,0:2386,3446|172,0:4818|173,0:6945|175,0:64|192,0:2090,10938,13616,23373|193,0:922|195,0:1007|213,0:5685,7026|221,0:3137|223,0:5078|230,0:3521|232,0:6286|239,0:1097|244,0:3552|247,0:3676|252,0:3895|263,0:2277|272,0:2590|274,0:5143"/><wd nm="tantiate" rd="78,0:1533|115,0:4298|127,0:3528|157,0:2043|160,0:3091|161,0:5156|203,0:684"/><wd nm="tantiated" rd="158,0:526|197,0:9920|203,0:1957"/><wd nm="tantiates" rd="85,0:474|161,0:7710"/><wd nm="tantiating" rd="197,0:8436|202,0:1283"/><wd nm="tantly" rd="9,0:647|27,0:3342|31,0:6600,10668|53,0:2438|54,0:5378,6561|67,0:2442|68,0:5151,9008|86,0:3504|88,0:7745,12823|89,0:7602,12838|90,0:7686,13275|91,0:7666,14389|92,0:7896,13163|93,0:7605,13121|94,0:7537|113,0:403|126,0:4177|138,0:3913|141,0:3185|145,0:1479|180,0:4552,10485|192,0:969,28986,29196,29226|195,0:1043|219,0:5771,9601|223,0:2435|224,0:5944,9797|232,0:3371|235,0:6626,10570|247,0:4026|248,0:3325|274,0:2448|275,0:5268,8992"/><wd nm="tants" rd="208,0:577"/><wd nm="taparameters" rd="72,0:10347,10442"/><wd nm="taplot" rd="88,0:3529|89,0:3367,7373|90,0:3460|91,0:3439|92,0:3681,8290|93,0:3396,7376,7999|96,0:1333|104,0:2721,4810,5037|106,0:2750,3638,4642,4791|149,0:4886,5013,5759,5896,6023,6864|162,0:1519,1987|167,0:1787,14906|204,0:4769|241,0:1536,2105|245,0:1924,14513|261,0:1883,1996|265,0:610,1040,6296,6471,7283,7381,7543,7602|266,0:1660,1717|267,0:978"/><wd nm="taplot&apos;s" rd="106,0:3826"/><wd nm="taplots" rd="88,0:29961,30045|89,0:28226,28310|90,0:8072,29981,30065,40274,40341,43446|91,0:8052,33525,33609,43990,44057,47162|92,0:30244,30328|93,0:28436,28520|195,0:1247"/><wd nm="taproviderpage" rd="86,0:384,460,512,738,1495,1551,2175,2265,2454,2626,2776,2879,3320,3370|248,0:371,427,653,1410,1466,2077,2264,2444,2594,2697,3138,3188"/><wd nm="taproviders" rd="88,0:1187,2035|89,0:1288,2064|90,0:1187,2017|91,0:1018,1823|92,0:1242,2150|93,0:1329,2105"/><wd nm="taqualifier" rd="110,0:1770,2050|111,0:2371,2650"/><wd nm="tar" rd="168,0:2668|175,0:348,2508,2596,4059,4143,4525|182,0:31712,31979,32119"/><wd nm="tarctica" rd="269,0:129,415"/><wd nm="tarea1" rd="92,0:1256,2164"/></pk>