<?xml version="1.0" encoding="UTF-8" standalone="no"?>
<pk><wd nm="r&apos;s" rd="17,0:240|18,0:2482|22,0:2139|30,0:253|33,0:762|74,0:1949|76,0:1280|88,0:42813|89,0:39385|90,0:44110|91,0:47826|92,0:43100|93,0:39587|94,0:929,3717,4030,6713,6794|97,0:819|105,0:12953|112,0:821,2307,2627|123,0:385|124,0:873|133,0:3404|135,0:1904|138,0:1335|141,0:2944,3435,3457|145,0:1348|152,0:4706,4991|182,0:32877|184,0:797|191,0:133|192,0:7395,7962,7983,8877,14973|196,0:6966|197,0:6741,6979|207,0:2193,6363|208,0:1287|209,0:766,836|210,0:3239,3524,10062,10347|211,0:1964,2249|213,0:4752,5037|214,0:3565,3850|225,0:2379,2409,4479|226,0:3862|227,0:3841,4601|228,0:1726|234,0:263|235,0:5669|241,0:3366|246,0:2561|249,0:1323|251,0:17438|255,0:19264"/><wd nm="r-riding" rd="113,128:4543"/><wd nm="r-side" rd="134,128:1065|135,128:3553|136,128:1088|137,128:1566|138,128:12244|151,128:3863"/><wd nm="r1" rd="27,0:6075|33,0:11252,11491|53,0:4908|67,0:4912|71,0:2767|98,0:1012|115,0:3650,3791,4017,10672,10813|116,0:2285|117,0:2770,3430,4153,5305,5373,6779,7517,7678|119,0:1882,2023,2318,3354,3495,4185,7198,7340|120,0:953|160,0:2925|223,0:4905|232,0:6113|247,0:3504|274,0:4970"/><wd nm="r1mc" rd="160,0:3184"/><wd nm="r1mc:movieclip" rd="160,0:2872"/><wd nm="r2" rd="117,0:2007,2317,2784,3915,4167|160,0:2997"/><wd nm="r2mc" rd="160,0:3284"/><wd nm="r2mc:movieclip" rd="160,0:2944"/><wd nm="r3" rd="160,0:3069"/><wd nm="r3mc" rd="160,0:3385"/><wd nm="r3mc:movieclip" rd="160,0:3016"/><wd nm="r:false" rd="207,0:27945,27966,29916,29937"/><wd nm="r:object" rd="155,0:1088"/><wd nm="r:visible" rd="211,0:8534|215,0:2315"/><wd nm="r_chart" rd="151,0:3154,3337|183,0:3758|184,0:3577"/><wd nm="r_name" rd="119,0:8882|120,0:2506"/><wd nm="r_programming_language" rd="128,0:2471"/><wd nm="r_thermometer" rd="140,0:2148"/><wd nm="ra" rd="17,0:5100|31,0:16422|54,0:11212|57,0:7908|60,0:8345|68,0:12787|82,0:368|88,0:14590|89,0:14605|90,0:15042|91,0:16156,19549|92,0:14867|93,0:14824|94,0:4294|139,0:2623|146,0:4113|167,0:7141|192,0:842,2702,19470|195,0:74|197,0:19122,23819|219,0:13972|224,0:14110|235,0:15341|245,0:7061|251,0:6831|255,0:7992|261,0:3586|275,0:12943"/><wd nm="rabic" rd="9,0:181"/><wd nm="rable" rd="0,0:476|70,0:1226|107,0:1448|124,0:888|128,0:9345|173,0:4660|218,0:771|231,0:157|256,0:267|264,0:173|266,0:185|267,0:2375,2617"/><wd nm="race" rd="24,0:578|51,0:575|58,0:577|65,0:579|80,0:604|156,0:1077|157,0:2303|159,0:479,708|165,0:577|173,0:576|174,0:1125,2608|176,0:6521,7901|221,0:574|230,0:587|244,0:578|252,0:576|272,0:582"/><wd nm="races" rd="24,0:1218|51,0:1215|58,0:1217|65,0:1219|80,0:1244|165,0:1217|173,0:1216|221,0:1214|230,0:1227|244,0:1218|252,0:1216|272,0:1222"/><wd nm="rack" rd="21,0:4701|23,0:3719|38,0:2202|50,0:2589|64,0:2164,2818|77,0:1728|79,0:237,418,1082,1222|86,0:773,3548|95,0:3800|112,0:1652|116,0:2429|123,0:356|133,0:8058|156,0:298|177,0:554|192,0:18589|196,0:10201|197,0:23160|220,0:2505,3596|227,0:4789|229,0:3701,4810|248,0:688,3369|271,0:2235"/><wd nm="racked" rd="201,0:6817|209,0:706"/><wd nm="racker" rd="23,0:1988|38,0:790|50,0:1584|64,0:1592|77,0:1313|85,0:2116|220,0:1583|229,0:2038|237,0:913,1475|271,0:1598"/><wd nm="rackets" rd="11,0:2482|24,0:1098|51,0:1095|58,0:1097|65,0:1099|80,0:1124|165,0:1097|173,0:1096|221,0:1094|230,0:1107|244,0:1098|252,0:1096|272,0:1102"/><wd nm="racking" rd="116,0:244|195,0:2846|239,0:559"/><wd nm="racks" rd="206,0:3461"/><wd nm="racle" rd="142,0:439|190,0:1965"/><wd nm="ract" rd="38,0:2458|40,0:10556|88,0:29903|89,0:28168|90,0:29923|91,0:33467|92,0:30186|93,0:28378|94,0:3771|95,0:4056|99,0:1453,5051|119,0:6313|127,0:3211|146,0:1517|162,0:1371,1853|163,0:498,1056,1350|165,0:2137|167,0:674,977,17015|192,0:13373|245,0:16622"/><wd nm="racter" rd="5,0:1967,2058,2094,3291|8,0:2472|10,0:260,407,1046,1154,1201,1348,1978,2084,2133,2280,2912,3019,3068,3215,3854,3876,3922,3949,4029,4237,4283,4430,5062,5085,5131,5159,5239,5450|11,0:305,444,493,604,1199,1303,2148,3355,3494,3878,3994,4070,4860,4970,5234,5868,5968|19,0:2478|31,0:17513,17627,17791,22974|48,0:1655,1668|54,0:12315,12429,12593,17762|57,0:8984,9098,9262,15341|60,0:9436,9550,9714,16533|68,0:13890,14004,14168,19341|74,0:722,2875|82,0:2963|83,0:587|88,0:13209,15695,15809,15973,31815,32158|89,0:13224,15710,15824,15988,30080,30423|90,0:13661,16147,16261,16425,31835,32178|91,0:14775,17261,17375,17539,20593,35379,35722|92,0:13549,15972,16086,16250,32098,32441|93,0:13507,15929,16043,16207,30289,30632|95,0:2461,2488|102,0:345,423,527|110,0:1614,1707,1813,1922,2015|111,0:1828,1883,2215,2308,2413,2522,2615|122,0:513,527|130,0:572,602|136,0:513,527|143,0:2700|154,0:1232|167,0:5083,8183,8299,8463,17821,18165|182,0:14463|217,0:2067|219,0:15063,15177,15341,20518|224,0:15201,15315,15479,20652|226,0:2309|235,0:16432,16546,16710,21883|245,0:5229,8096,8210,8374,17433,17777|246,0:1331,3487|251,0:7866,7980,8144,14832|255,0:9083,9197,9361,16892|259,0:9641|263,0:4178|269,0:1153|275,0:14048,14162,14326,19493"/><wd nm="racters" rd="5,0:3063|6,0:1321|9,0:125,228,485,553,584,1329|11,0:92,1353,1399,1561,2112,2421,3191|27,0:2801,5530|31,0:10127|53,0:1897,4363|54,0:6020|67,0:1901,4367|68,0:8467|71,0:2222|72,0:3080|74,0:3394|80,0:3600|88,0:8749,11666,40992|89,0:8606,11681,38100|90,0:9201,12118,41765|91,0:9218,13232,45481|92,0:9296,12006,41278|93,0:9004,11964,38303|94,0:1802,1880,2045,5234,5270,7340,7469,7782,8547,8625,8790|95,0:2223,2344|98,0:467|101,0:1368|102,0:2935|103,0:6584|107,0:2749|108,0:4312|109,0:1651,1668,4233|110,0:1583,1891|111,0:2184,2491|143,0:2362,2533,2577,2679|154,0:1140|167,0:20315|219,0:9060|223,0:1894,4360|224,0:9256|232,0:2830,5568|235,0:10029|239,0:2558,3492|245,0:19937|246,0:4006|263,0:1194,3658,4102,4225|274,0:1907,4425|275,0:8451"/><wd nm="racterset" rd="9,0:2837"/><wd nm="ractice" rd="143,0:1709|147,0:4858"/><wd nm="racting" rd="59,0:230|161,0:5634"/><wd nm="raction" rd="17,0:312|27,0:2004|33,0:834|50,0:2852|53,0:1100|64,0:2427,3081|67,0:1104|74,0:4800|77,0:1991|141,0:3099|162,0:4021|190,0:4178|192,0:9557|220,0:3859|223,0:1097|229,0:5073|232,0:2033|237,0:1696|242,0:1720|246,0:5412,7665|260,0:8760|271,0:2498|274,0:1110"/><wd nm="ractive" rd="0,0:519|79,0:6400|82,0:3308,3364,3427,3982|84,0:1594|164,0:1295|168,0:2030|190,0:317,1725|195,0:3349,5516,6141|197,0:22657|202,0:2524|243,0:526"/><wd nm="ractivelegend" rd="82,0:4040,4071|88,0:29852|89,0:28117|90,0:29872|91,0:33416|92,0:30135|93,0:28327|167,0:16954|245,0:16561"/><wd nm="ractivity" rd="146,0:426,2153"/><wd nm="racts" rd="183,0:732"/><wd nm="racy" rd="31,0:7801|68,0:6352|219,0:6972|224,0:7141|235,0:7826|275,0:6469"/><wd nm="rade" rd="127,0:2695,4499|190,0:2181|192,0:259,1463,3022|194,0:570"/><wd nm="radial" rd="18,0:5456|22,0:116,393,407,1408,1547|26,0:114|31,0:13041,13079|32,0:935,4810,4869|34,0:1089,1295,5085,5144|41,0:5357,5416|42,0:5370|45,0:1556,1707,1857,2927,3056,3184|46,0:11619,11678"/><wd nm="radient" rd="12,128:5,31,74,163,246,283,412,453,586,608,953,1877,2050,2226,2652,2880,2961,3240|18,0:173,932,994,1031,1313,1361,1464,3007,4145,5010,5332,5463|20,0:428,763,848|31,0:12095,12114,12428,13009,13069,13085,13096,13125,13148,13210,18993,19059,19248,19391,19552|32,0:773,808,901,1044,1111,3573,3697,3763,3847,3973,4109,4211,4389,4526,4549,4686,4776,4839|34,0:543,601,988,1032,1062,1167,1201,1301,1347,1599,3848,3972,4038,4122,4248,4384,4486,4664,4801,4824,4961,5051,5114|37,0:395|41,0:715,751,931,1016,1147,1217,1401,1508,1542,4120,4244,4310,4394,4520,4656,4758,4936,5073,5096,5233,5323,5386|42,0:640,711,1111,1155,1197,1284,1412,1479,1641,1748,1763,1882,4128,4252,4318,4402,4528,4664,4768,4946,5086,5109,5246,5336,5399|46,0:10391,10515,10581,10665,10791,10927,11029,11207,11335,11358,11495,11585,11648|47,0:691|54,0:7476,13795,13861,14050,14193,14354|55,0:1950,1984,2240|57,0:11273,12116,12182,12371,12514,12675|60,0:11720,12562,12628,12817,12960,13121|68,0:15370,15436,15625,15768,15929|74,0:3835|88,0:19201,19346,19432,19497,19544,21093,21159,21374,21543,21730,24266,24368,24568,38232|89,0:7147,7417,7472,19231,19278,19353,19400,19465,19512,19567,19712,19798,20107,20173,20388,20557,20744,23280,23382,23582,36551|90,0:21127,21193,21382,21525,21686,24196,24298,24498,38346|91,0:24457,24523,24738,24907,25094,27630,27732,27932,42062|92,0:19486,19631,19717,19782,19829,21377,21443,21658,21827,22014,24550,24652,24851,38518|93,0:7150,7420,7475,19448,19495,19570,19617,19682,19729,19784,19929,20015,20323,20389,20604,20773,20960,23494,23596,23796,36755|100,0:2507,2573,2762,2905,3066|167,0:10995,11061,11250,11393,11554|177,0:3087|182,0:9188,9254,9443,9585,9746,11331,11433,11615,12560,12606,12774,12860,23649,23683,25063,25097|195,0:1865,4262,4303,5311,6658|219,0:16544,16610,16799,16942,17103|224,0:16681,16747,16936,17079,17240|225,0:302,2964,3024,3061,3338,3490,4994|235,0:11213,11232,11546,17912,17978,18167,18310,18471|245,0:10600,10666,10855,10998,11159|246,0:4447|251,0:4789,10121,10187,10376,10519,10680,13190,13292,13492|255,0:12918,12984,13173,13316,13477|259,0:3915,5670,5736,5925,6068,6229|275,0:4510,15519,15585,15774,15917,16078"/><wd nm="radientcolor" rd="88,0:19155|89,0:1464,2260,19521|92,0:1495,2429,19440|93,0:1488,2282,19738"/><wd nm="radients" rd="31,0:19158,19332,19485,19582|54,0:13960,14134,14287,14384|57,0:12281,12455,12608,12705|60,0:12727,12901,13054,13151|68,0:15535,15709,15862,15959|88,0:21266,21466,21645,21768,24486|89,0:20280,20480,20659,20782,23500|90,0:21292,21466,21619,21716,24416|91,0:24630,24830,25009,25132,27850|92,0:21550,21750,21929,22052,24769|93,0:20496,20696,20875,20998,23714|100,0:2672,2846,2999,3096|167,0:11160,11334,11487,11584|182,0:9353,9527,9679,9776,11533,12683,12912|190,0:1331|219,0:16709,16883,17036,17133|224,0:16846,17020,17173,17270|225,0:3393|235,0:18077,18251,18404,18501|245,0:10765,10939,11092,11189|251,0:10286,10460,10613,10710,13410|255,0:13083,13257,13410,13507|259,0:5835,6009,6162,6259|275,0:15684,15858,16011,16108"/><wd nm="rading" rd="127,0:2801|192,0:28,186,1595,1682,34496,35378|193,128:0,25,148,404,1528|194,128:0,37,175,1208"/><wd nm="radio" rd="188,0:2107"/><wd nm="raditional" rd="86,0:719|190,0:3260|248,0:634"/><wd nm="radius" rd="16,0:1162,1199,1227,1281,1352,4266,4371,4440,4632|17,0:1188,1199,2546,3185,3728,4104,4126,5358|18,0:226,238,1599,1635,3608,3622,3660,3704,3726,3758,3780,3842,3867,3901,3923,3956,3978,4154,4172,4226,4254,5148,5258,5630,5812|20,0:181,1510,1583,1652,1700,1981,2782,2982|22,0:1339|30,0:1623,1645,1685,1730,2213,2241,2350,2420,2432,2473,2484,2545,3241,3372,4022,4108,4120,4208,4219|31,0:4756,4855,4978,5313,5413,5537,8665,11885,11922,11950,12004,12075,12819,12846,25374,25629,25636,25711|32,0:252,382,413,460,497,530,1616,1627,1895,1905,2709,2726,2741,2768,2805,2812,2832,5338,5350,5623,5634|33,0:2088,6918,7018,7145,7261,7399,7605,7702,7827,7941,8027,8576,8672,8795,8907,9051,9265,9358,9479,9589,9683,11416,11673,12077,14665,14684,14715,14816,15014,15104,15221,15327,15459,15876,15896,15929,16041,16235,16320,16433,16535,16641|34,0:240,380,503,779,919,2071,2284,3050,3067,3085,3105,5753,5852,5980,6097,6246,6521,6606,6719,6821,6931|36,0:2059,2165,2538,2627|37,0:1636,1655,1686,1787,1998,2094,2217,2329,2473,3249,3269,3302,3414,3596,3689,3810,3920,4014,5427,5970|39,0:2758,3742|40,0:1245,1264,3307,3326,3357,3507,3583,3670,3828,3915,4357,4378,4413,4597,4686,4788,5001,5076,6580,6587,6597,9341,9353|41,0:283,433,2250,2475,3397,3414,3433,3453|42,0:2074,2442,2653,3710,3727,5916,6022,6249,6338|44,0:4266,4387,5419,5528|45,0:1535,1686,1836,2905,3034,3162|46,0:6806,6823,6868,6893,6913,6999,7026,7063|47,0:806,872,930|54,0:3484,3575,3698,4045,4137,4261,7223,7260|57,0:11659,11747|60,0:12106,12194|61,0:184,904,1137,1205,1278|68,0:3555,3686,4033,4128,4260,9505,9530|88,0:20285,20333,20370,39092,39140,39200,42022,42075|90,0:20319,20367,20404,39511,39559,39619,42796,42849|91,0:23649,23697,23734,43227,43275,43335,46512,46565|92,0:20569,20617,20654,39378,39426,39486,42309,42362|99,0:438,521,604,4227,4294,4361|150,0:4537,5140|179,0:5171,5211,5243|182,0:12359,12466,32132,32152|189,0:4312|192,0:10302|195,0:4347|219,0:4613|224,0:4736|225,0:1508,1560,1601,5659,5690|228,0:1151|234,0:1840,1868,2559,2691|235,0:4672,4765,4894,5241,5335,5465,11088,11179,11939,11968,24821,24843,26186,26214|253,0:2762,2854,3085|255,0:10842,10890,10927|268,0:216,1264,1343,1421,1464|275,0:3420,3510,3636,3983,4074,4201,9382,9440"/></pk>