<?xml version="1.0" encoding="UTF-8" standalone="no"?>
<pk><wd nm="nvas" rd="0,0:2255|16,0:4291|24,0:1641,1701|31,0:18817,22507,22631,22797|40,0:6756,6790,7651,7682,7817,7939,8048,8147,9384,9444,9465,9519,9552,9586,9619,9650,9689,9728,9755,9784|51,0:1638,1698|54,0:13619,17295,17419,17585|57,0:11940,14873,14997,15163,16315,16384,16903,16909,16987,16993|58,0:1640,1700|60,0:12386,16066,16190,16356,17565,17634,18153,18159,18237,18243|65,0:1642,1702|68,0:15194,18874,18998,19164|70,0:304,2996,3130,3476,4001,4063,4261,4318,4449|72,0:2916|73,0:654|75,0:122|77,0:895|80,0:1674,1734|82,0:3235|85,0:911,1577|87,0:101|88,0:283,3032,3968,4932,20917,24067,24084,24174,24242,24349,24462,24539,24619,24688,24770,24979,27152,28049,28173,28339,28481,28541,28713,28890,33046,33126,33261,33418,33575,33702,33825,33927,33971,34371,34890,34896,34974,34980,35050,35105,42666|89,0:289,2870,3702,4381,19931,23081,23098,23188,23256,23363,23476,23553,23633,23702,23784,23993,25417,26315,26439,26605,26747,26807,26979,27156,31311,31391,31590,31747,31874,31997,32099,32143,32511,32945,33464,33470,33548,33554,33624,33679,39238|90,0:283,2963,3910,4874,8308,8416,20951,23997,24014,24104,24172,24279,24392,24469,24549,24618,24700,24909,27172,28070,28194,28360,28502,28562,28734,28911,33066,33146,33281,33438,33595,33722,33845,33947,33991,34394,34913,34919,34997,35003,35073,35128,40586,40694,43676,43782,43963|91,0:297,2942,3889,4853,8288,8396,24281,27431,27448,27538,27606,27713,27826,27903,27983,28052,28134,28343,30605,31613,31737,31903,32045,32105,32277,32454,36610,36690,36825,36982,37139,37266,37389,37491,37535,37938,38457,38463,38541,38547,38617,38672,44302,44410,47392,47498,47679|92,0:304,3184,4120,5084,21201,24351,24368,24458,24526,24633,24745,24822,24902,24971,25053,25262,27435,28332,28456,28622,28764,28824,28996,29173,33329,33409,33544,33701,33858,33985,34108,34210,34254,34657,35176,35182,35260,35266,35336,35391,42953|93,0:311,2909,3725,4396,20147,23296,23312,23402,23470,23577,23690,23767,23847,23916,23998,24206,25629,26525,26649,26815,26957,27017,27189,27366,31519,31599,31798,31955,32082,32205,32307,32351,32719,33153,33672,33678,33756,33762,33832,33887,39440|94,0:3373,10118|96,0:1200|97,0:3582,3742,3799,3925,3976,4105,4285|154,0:1591,1653|165,0:1640,1700|167,0:1453,10819,14501,14625,14791,19052,19132|173,0:1639,1699|182,0:3290,8792,11307,11414,11509,11586,11666,11735,11817,16317,17583,17663,17801,32730|192,0:20069,20096,20216,20281,29800,29862,30060,30117,30248,33383|195,0:3195,3246|205,0:2894,3054,3111,3237,3288,3420,3600|209,0:1094,1121,1257,1322,3328|219,0:16368,20050,20174,20340|221,0:1637,1697|224,0:16505,20185,20309,20475|230,0:1650,1710|235,0:17736,21416,21540,21706|244,0:1641,1701|245,0:1582,10424,14106,14230,14396,18665,18745|251,0:198,1528,1535,9945,12991,13008,13098,13166,13273,13386,13463,13543,13612,13694,14364,14488,14654,15868,16730,16736,16814,16820,17291|252,0:1639,1699|255,0:12742,16424,16548,16714,17934,18556,18562,18640,18646,19117|259,0:5494,9174,9298,9464,10682,11614,11620,11698,11704|260,0:2676,2883,3467,3623,3711,3819,3930,4529,4593,4836,5279,5347,5467,5489,5778,5864,6240,6353,7085,7145,7166,7220,7253,7287,7320,7351,7390,7429,7456,7485,8233,8494|265,0:557,993,6243,6423|272,0:1645,1705|275,0:15343,19025,19149,19315"/><wd nm="nvasbgalpha" rd="88,0:24309|89,0:23323|90,0:24239|91,0:27673|92,0:24593|93,0:23537|182,0:11374|197,0:10785|251,0:13233"/><wd nm="nvasbgangle" rd="88,0:24496|89,0:23510|90,0:24426|91,0:27860|92,0:24779|93,0:23724|182,0:11543|251,0:13420"/><wd nm="nvasbgcolor" rd="88,0:969,1793,24214|89,0:1003,1751,23228|90,0:969,1787,24144|91,0:27578|92,0:1024,1908,24498|93,0:1044,1792,23442|182,0:11279|251,0:13138"/><wd nm="nvasbgratio" rd="88,0:24409|89,0:23423|90,0:24339|91,0:27773|92,0:24692|93,0:23637|182,0:11473|251,0:13333"/><wd nm="nvasborderalpha" rd="88,0:24710|89,0:23724|90,0:24640|91,0:28074|92,0:24993|93,0:23938|182,0:11757|251,0:13634"/><wd nm="nvasbordercolor" rd="88,0:945,1767,24577|89,0:979,1725,23591|90,0:945,1762,24507|91,0:27941|92,0:1000,1882,24860|93,0:1020,1766,23805|182,0:11624|251,0:13501"/><wd nm="nvasborderthickness" rd="88,0:922,1742,24637|89,0:23651|90,0:922,1738,24567|91,0:28001|92,0:977,1857,24920|93,0:23865|182,0:11684|251,0:13561"/><wd nm="nvasbottommargin" rd="70,0:3546|88,0:35057|89,0:33631|90,0:35080|91,0:38624|92,0:35343|93,0:33839"/><wd nm="nvascenterx" rd="33,0:11920|40,0:7786,9658|260,0:7359,7788,7957"/><wd nm="nvascentery" rd="40,0:7908,9697|260,0:7398,7870,8033"/><wd nm="nvasendx" rd="40,0:9527|260,0:7228"/><wd nm="nvasendy" rd="40,0:7626,9594|260,0:7295"/><wd nm="nvases" rd="70,0:3692"/><wd nm="nvasheight" rd="40,0:8126,9763|260,0:7464"/><wd nm="nvasleftmargin" rd="57,0:16859|60,0:18109|70,0:3269,3380,3412,3783|75,0:614,1464|88,0:34846|89,0:1493,2293,33420|90,0:34869|91,0:38413|92,0:35132|93,0:1525,2323,33628|251,0:16686|255,0:18512|259,0:11570"/><wd nm="nvaspadding" rd="88,0:33204|90,0:33224|91,0:36768|92,0:33487"/><wd nm="nvasrightmargin" rd="57,0:16941|60,0:18191|70,0:3512|88,0:34928|89,0:33502|90,0:34951|91,0:38495|92,0:35214|93,0:33710|251,0:16768|255,0:18594|259,0:11652"/><wd nm="nvasstartx" rd="40,0:9371|260,0:7072"/><wd nm="nvasstarty" rd="40,0:9452,10369,10469|260,0:5734,5991,6075,7153,7592,7678,8339,8426,8596,8683"/><wd nm="nvastopmargin" rd="70,0:3530|88,0:35008|89,0:33582|90,0:35031|91,0:38575|92,0:35294|93,0:33790"/><wd nm="nvaswidth" rd="40,0:8029,9736|260,0:7437"/><wd nm="nvbasefont" rd="31,0:22419|54,0:17207|57,0:14785|60,0:15978|68,0:18786|88,0:27961,28390|89,0:26227,26656|90,0:27982,28411|91,0:31525,31954|92,0:28244,28673|93,0:26437,26866|167,0:14413|219,0:19962|224,0:20097|235,0:21328|245,0:14018|251,0:14276|255,0:16336|259,0:9086|275,0:18937"/><wd nm="nvbasefontcolor" rd="88,0:28763|89,0:1136,1900,27029|90,0:28784|91,0:32327|92,0:29046|93,0:1177,1941,27239"/><wd nm="nvbasefontsize" rd="88,0:28591|89,0:26857|90,0:28612|91,0:32155|92,0:28874|93,0:27067"/><wd nm="nvelope" rd="31,0:15039|54,0:9761|68,0:11336|88,0:18446|89,0:18461|90,0:18898|91,0:22229|92,0:18731|93,0:18679|219,0:12532|224,0:12727|235,0:13902|236,0:250,891,1158|240,0:2634,2776|275,0:11552"/><wd nm="nveloped" rd="24,0:562|51,0:559|58,0:561|65,0:563|80,0:588|165,0:561|173,0:560|221,0:558|230,0:571|244,0:562|252,0:560|272,0:566"/><wd nm="nvention" rd="6,0:1104|180,0:523"/><wd nm="nventional" rd="6,0:1714|211,0:8019|215,0:396"/><wd nm="nventions" rd="138,0:3622"/><wd nm="nventory" rd="66,0:153"/><wd nm="nversion" rd="128,0:2611|145,0:1280|162,0:1117,1589|163,0:162,864,1141|165,0:1919,2458,2566|167,0:463,759|187,0:2321"/><wd nm="nvert" rd="5,0:1192,1494|7,0:1004,3074|8,0:468,3511|11,0:1450|31,0:18149,18544|54,0:12951,13346|57,0:9620,10015|60,0:10072,10467|68,0:14526,14921|72,0:4297,5548,9486|79,0:3791|82,0:2113|83,0:1123|88,0:16329,16722|89,0:16344,16737|90,0:16781,17174|91,0:17895,18288|92,0:16610,17007|93,0:16563,16956|99,0:1690,5256,6680|124,0:1428|125,0:476|128,0:1239,2578|137,0:1037|140,0:216|142,0:861|144,0:144,1146|145,0:783,1247|146,0:7031|148,0:285,2724,3430|158,0:258|160,0:4038|161,0:1073,3884|164,0:1495|167,0:8833,9228|172,0:361|187,0:2364|192,0:2547,5348|195,0:5711,6226|214,0:6375,6441|219,0:15699,16094|224,0:15837,16232|235,0:17068,17463|243,0:611|245,0:8740,9135|251,0:8502,8897|255,0:9719,10114|275,0:14679,15069"/><wd nm="nverted" rd="5,0:1689|6,0:1633|7,0:4476,4521,4567|8,0:1575,1705,1873,1912,2001,2053|31,0:16398|54,0:11188|57,0:7884|68,0:12763|72,0:10504|88,0:14566|89,0:14581|90,0:15018|91,0:16132,19525|92,0:14843|93,0:14800|99,0:3347,6593,8017|163,0:758,802,2072|166,0:712|167,0:7117|171,0:1156|176,0:1650|209,0:3802|219,0:13948|224,0:14086|235,0:15317|242,0:453|245,0:7039|251,0:6807|255,0:7968|258,0:228|275,0:12919"/><wd nm="nverter" rd="148,0:2709|187,0:2451"/><wd nm="nverting" rd="6,0:224|8,0:1813|31,0:18061,18456|54,0:12863,13258|57,0:9532,9927|60,0:9984,10379|68,0:14438,14833|88,0:16238,16631|89,0:16253,16646|90,0:16690,17083|91,0:17804,18197|92,0:16515,16912|93,0:16472,16865|126,0:1427,2963|140,128:0,3196|167,0:8737,9140|176,0:1616|192,0:458,5209,5561|219,0:15611,16006|224,0:15749,16144|235,0:16980,17375|245,0:8644,9047|251,0:8414,8809|255,0:9631,10026|275,0:14591,14981"/><wd nm="nverts" rd="96,0:2651|125,0:652|154,0:1216|192,0:20035|209,0:1060"/><wd nm="nvestment" rd="0,0:627,1288"/><wd nm="nvey" rd="6,0:1280|19,0:657|31,0:4643,5198|54,0:3371,3930|68,0:3355,3918|115,0:4114|127,0:3270|156,0:405|157,0:2201|160,0:3448,4264|161,0:5915,9901|166,0:1654|197,0:18148|217,0:858|219,0:3951,4498|224,0:4074,4621|226,0:661|235,0:4559,5126|275,0:3307,3868"/><wd nm="nveyed" rd="127,0:3399"/><wd nm="nvinced" rd="160,0:4762"/><wd nm="nvironment" rd="86,0:897|195,0:2989|248,0:812"/><wd nm="nvoke" rd="31,0:6013|54,0:4791|57,0:3764|60,0:3731|68,0:4564|86,0:3347|88,0:7158|89,0:6460|90,0:7099|91,0:7079|92,0:7309|93,0:6463|103,0:151,6391|105,0:4678|115,0:640,5580|116,0:167|125,0:1431,2333,2644|128,0:855,8926|144,0:954|145,0:3846|167,0:3382|182,0:8078|196,0:7846|208,0:2370,2435|219,0:5184|224,0:5357|235,0:6039|245,0:3524|248,0:3165|251,0:4102|255,0:5516|259,0:3228|275,0:4681"/><wd nm="nvokecss" rd="209,0:3611"/><wd nm="nvoked" rd="27,0:340,2954|31,0:10280|53,0:350,2050|54,0:6173|67,0:354,2054|68,0:8620|78,0:1633|79,0:2565,3722|86,0:594|88,0:11819|89,0:11834|90,0:12271|91,0:13385|92,0:12159|93,0:12117|94,0:4520|96,0:1447,2557,5231|101,0:530|103,0:938,1959|105,0:1857|108,0:955|109,0:1013|112,0:1899,2560|115,0:5748,6167|116,0:313,623,1596|124,0:1131|127,0:2275|128,0:469|138,0:9917,10298,11142|149,0:7486|192,0:20174|197,0:18139|207,0:1972|209,0:1215,4271|219,0:9213|223,0:349,2047|224,0:9409|232,0:340,2983|235,0:10182|236,0:1686|248,0:509|274,0:355,2060|275,0:8604"/><wd nm="nvokes" rd="86,0:3313|107,0:2304|109,0:1753|115,0:5686|142,0:1223|149,0:7805|185,0:731|248,0:3131"/><wd nm="nvoking" rd="96,0:2681,2750|101,0:1306|102,0:2873|103,0:6522|107,0:2687|108,0:4250|109,0:4171|110,0:250|115,0:5619|190,0:2785"/><wd nm="nvolved" rd="19,0:206|48,0:158|56,0:183|94,0:5739|114,0:343|118,0:165|128,0:5271|137,0:662|163,0:251|166,0:323|183,0:312|185,0:970,1388|188,0:661|217,0:500|226,0:210|240,0:337|269,0:198"/><wd nm="nvolves" rd="123,0:934|142,0:532|149,0:2214|188,0:87|260,0:2774"/><wd nm="nvolving" rd="27,0:152|53,0:162|67,0:166|125,0:112,2833|223,0:161|232,0:152|274,0:167"/></pk>