<?xml version="1.0" encoding="UTF-8" standalone="no"?>
<pk><wd nm="etscape" rd="108,0:2051,2198"/><wd nm="etseconds" rd="78,0:921"/><wd nm="etsv3.1" rd="192,0:35444"/><wd nm="ette" rd="17,0:2567,3206|18,0:478,526,554,636,655,712,858|19,0:1314,1680,2368,2398,2658,2839|21,0:1384,1941|23,0:3163|24,0:2031|27,0:3587,4205|28,0:390,1107|31,0:623,989,3647,3729,3835,3955|45,0:1029,2423|53,0:2692,3236|54,0:2331,2413,2519,2636|55,0:501,549,577,659,678,697,754,839,889,923|57,0:3117,3199,3305,3422|60,0:3084,3166,3272,3389|61,0:442,490,518,605,622,679,820|62,0:829,929,1338,1359,1451,1538|65,0:1917|67,0:2696,3240|68,0:428,528,2362,2444,2550,2667|70,0:608,656,677,766,784,806,824,877,1020|84,0:1806|88,0:6574,6656,6762,6879|89,0:5876,5958,6064,6181|90,0:6515,6597,6703,6820|91,0:926,1728,6495,6577,6683,6800|92,0:6725,6807,6913,7030|93,0:5879,5961,6067,6184|140,0:1167,1340|150,0:5062|152,0:2170|157,0:708|160,0:1727,2273,2528|161,0:4266|167,0:2735,2817,2923,3040|169,0:757,805,833,925,943,967,985,1038,1179|174,0:692,2196|176,0:6088,7489|182,0:8847,8888,8944,9061|192,0:27313,27420|195,0:1881|197,0:15508,15534,15652|211,0:7794|214,0:9513,9534,9641,9956|216,0:426,474,560,579,636,743|217,0:1139,1430,2007,2028,2237,2369|219,0:574,865,2908,2990,3096,3213|221,0:1980|223,0:2689,3233|224,0:3081,3163,3269,3386|225,0:579,627,655,737,756,775,832,976|226,0:1286,1621,2253,2274,2479,2610|227,0:1357,1870|230,0:2018|232,0:3626,4254|235,0:589,933,3566,3648,3754,3871|245,0:2877,2959,3065,3182|250,0:269,595,1002|251,0:491,817,3455,3537,3643,3760|252,0:1996|254,0:287,1157,2017|255,0:494,1363,4869,4951,5057,5174|259,0:2528,2610,2716,2833|268,0:451,499,527,616,626,642|269,0:654,737,1131,1184,1237,1306|272,0:1926,2254,2347|274,0:2702,3252|275,0:449,532,2314,2396,2502,2619"/><wd nm="ettecolors" rd="192,0:27323,27430|197,0:15662|211,0:7804|214,0:9544"/><wd nm="etter" rd="8,0:196|37,0:12313|44,0:3540|46,0:9675|72,0:2981|88,0:10979|89,0:10841|90,0:11431|91,0:12545|92,0:11319|93,0:11029|104,0:486|106,0:483|115,0:3463|119,0:1692|161,0:5681,9438|174,0:565|180,0:4946,10812|184,0:298|189,0:4157|192,0:14659,15249|195,0:609,1933,6709,6844,6964,7057|198,0:490,512,552|208,0:223,701,884,1112,4095|225,0:1198|264,0:1923|267,0:1181"/><wd nm="etterspacing" rd="44,0:3516|46,0:9651|263,0:1131,3960,4030,4393,4546,4647,4661,4691"/><wd nm="etterthemecolor" rd="18,0:809|55,0:862"/><wd nm="ettes" rd="18,0:148,338,385,422,599|31,0:3696|54,0:2380|55,0:181,361,408,445,622|57,0:3166|60,0:3133|61,0:149,301,349,386,563|68,0:2411|70,0:185,454,515,552,719|88,0:6623|89,0:5925|90,0:6564|91,0:6544|92,0:6774|93,0:5928|167,0:2784|169,0:362,608,664,701,878|177,0:2753|195,0:2706,5199|216,0:139,290,333,370,523|219,0:2957|224,0:3130|225,0:140,439,486,523,700|235,0:3615|245,0:2926|251,0:3504|255,0:4918|256,0:813,841|259,0:2577|268,0:154,307,358,395,572|275,0:2363"/><wd nm="ettethemecolor" rd="18,0:771|31,0:3791|54,0:2475|55,0:813|57,0:3261|60,0:3228|61,0:738,774|68,0:2506|70,0:936,972|88,0:6718|89,0:6020|90,0:6659|91,0:6639|92,0:6869|93,0:6023|167,0:2879|169,0:1097,1133|182,0:8902|216,0:695|219,0:3052|224,0:3225|225,0:891,929|235,0:3710|245,0:3021|251,0:3599|255,0:5013|259,0:2672|268,0:665|275,0:2458"/><wd nm="etthickness" rd="55,0:1145,1234|57,0:10957|60,0:11405"/><wd nm="ettime" rd="72,0:10330"/><wd nm="etting" rd="0,128:0,29,1994,2248,2956,3192,3452,5178,6142|1,0:2416,3541,4064,4684|4,0:623|5,0:341,1800,1927|7,0:436|8,0:1568|9,0:1160|14,128:13,26,3044|16,0:3897|17,0:6117|18,0:721,3381|19,0:370|21,0:250|24,0:1629|27,0:958|29,0:232,544,1011,2083|30,0:2101,2618,2743|31,0:4416,4531,6098,14393|32,0:550,687,960,1390|33,0:2429,3275,4708,5526,10063,16905,17252|34,0:1240,1409,1858|36,0:685|39,0:528,679,782|41,0:606,1617,1863,2002|42,0:1538,2195|44,0:1019,1246,1425|45,128:11,30,754,4133|48,0:322|51,0:1626|53,0:835|54,0:3097,3212,3259,4876,9115|55,0:763,4062|57,0:3854|58,0:1628|60,0:3816,4354|61,0:198,688,1370,2392|65,0:1630|67,0:839|68,0:3128,3243,4649,10690|69,0:695,3641|70,0:886,1305|72,0:8525|74,0:1702|76,128:21,48,147,1455|79,128:21,49,6640|80,0:1662|84,0:148|85,0:207,1180|86,0:2057|87,0:2422,2876|88,0:7243,8007,17819,19889,30123,30614,31208|89,0:6545,7864,17834,28388,28879,29473|90,0:7184,8459,18271,19923,30143,30634,31228|91,0:7164,8439,21602,23254,33687,34178,34772|92,0:7394,8161,8554,18104,20174,30406,30897,31491|93,0:6548,7870,8263,18052,28598,29089,29683|94,0:1434,1965,4686,5176,7103,8179,8710|96,0:1933,1979|100,0:2257|104,0:4115|105,0:14942|107,0:208|110,0:133,380|111,0:438,1193|112,128:41,68,5355|115,128:41,54,93,13156|116,128:47,74,3281|119,0:103|122,0:156|125,0:2787|126,0:5190|127,0:773|129,0:3519|135,0:646,2742,3134|136,0:156|138,0:1286,9777|141,0:676,1466,2680|145,0:2590|152,0:952,987|153,0:3203|154,0:1579|161,0:1636|162,0:2566,2906,3549,3841|163,0:2105|165,0:1628|166,0:1747,1815|167,0:3467,4005,5773,15450,16281,16930|169,0:1047,1744,4405,4563,5030,6480|171,0:207,276|173,0:1627|174,0:4006|175,0:4790|179,0:601,987,1178,5678|182,0:6561,6852,8163,14049,15451,16045|188,0:1320|189,0:1781|192,0:1067,1104,9452,9581,10639,11667,12014,23858,23871,26977,28855,30974,31203,32035|197,0:1947,13539,13722,20007,21039|200,0:4702,5466|202,128:0,23,318,853,2441,3351|204,128:0,26,3535,5063,5713,8424|210,0:1966,8400|213,0:1078,1116|214,0:4559,6887,8402,9189|216,0:645,2756|219,0:3724,3839,5269,11886|221,0:1625|223,0:832|224,0:3847,3962,5442,12081|225,0:841,5365|226,0:374|227,0:251|230,0:1638|232,0:962|233,0:549|234,0:1728,1987|235,0:4332,4447,6124,13256,26074|236,0:639,1182|238,0:1448|240,128:14,27,631,2002,3245|241,0:2773,3079,3263|242,0:1338|244,0:1629|245,0:3609,4147,15057,15888,16537|246,0:2314,6474|247,0:133|248,0:1972|249,0:2105|251,0:4187,4978|252,0:1627|253,0:1878,3281,4246|255,0:5601,6139|257,0:1796|259,0:3313,4112|260,0:2579,4448|261,0:2065,2422|263,0:1958|264,0:1080|265,0:1709|266,0:1240,1835|268,0:198,1246,2500|272,0:1633|274,0:845|275,0:3080,3195,4766,10906"/><wd nm="ettings" rd="0,0:355|3,0:644|24,0:1441,2347|31,0:21241|38,0:2430|50,0:2817|51,0:1438,2201|54,0:16043|58,0:1440,2256|60,0:14810|64,0:2392,3046|65,0:1442,2055|68,0:17618|77,0:1956|80,0:1474,2794|88,0:23445|89,0:22459|90,0:23375|91,0:26809|92,0:23729|93,0:22675|94,0:3599,3701,3906,4098,6917|95,0:4028,4224|97,0:3048|105,0:1596|107,0:1423|126,0:459,2363,2514,3235,3286,3643|127,0:5852,6119,6150|131,0:1027,1481|138,0:1301,1755,7831|145,0:2664|149,0:7225|152,0:459,5055|165,0:1440,2246|167,0:13243|169,0:2165|173,0:1439,3194|182,0:13413|188,0:1302,1356,1555,1583,1612,1712,2032,2073,2494,2525,2666|189,0:4281|192,0:23808|197,0:16142,16709,16808,16861,17870,17944,18364,18464,18500,24489,24650,24686|200,0:218,3095|201,0:5001|203,0:1139|205,0:2360|207,0:1723|208,0:3357|210,0:3588,10411|211,0:2313,7473|212,0:1375|213,0:474,5101,9547,9916|214,0:3914|215,0:505|219,0:18792|220,0:3824|221,0:1437,2243|224,0:18929|229,0:5038|230,0:1450,2347|235,0:20160|237,0:1661|244,0:1441,2350|245,0:12848|251,0:12369|252,0:1439,2961|255,0:15166|259,0:7918|271,0:2463|272,0:1445,2045|275,0:17767"/><wd nm="ettransparent" rd="197,0:10680,11046|198,0:1939|203,0:1199"/><wd nm="etty" rd="8,0:3265|37,0:11842|72,0:4800"/><wd nm="ettyphoto" rd="152,0:10565|207,0:2837,13963,14382,14398,14471,14492,14564,14719,14855,15296,15313,15350,15444,15622,15885,15901,15974,15995,16218,16261,16406,16491,16551,16591,16670,19813,20232,20248,20321,20342,20414,20569,20705,21146,21163,21200,21294,21472,21735,21751,21824,21845,22068,22111,22256,22341,22401,22441,22520,23060,23181,23198,23235"/><wd nm="etup" rd="94,0:4068|102,0:2184|114,0:1105|117,0:292|118,0:928|123,0:757,2148|124,0:1875|126,0:1565,4065,4613|128,0:5640|129,0:278|135,0:640,984|137,0:1348|138,0:5425,9829|145,0:2873,4232|148,0:1036|152,0:1392|157,0:1051|187,0:2492|188,0:1272,2636|200,0:519|207,0:26216,29627|208,0:3327|210,0:5609|211,0:6626|213,0:1789,8670|214,0:690|238,0:2054|240,0:842|247,0:2048,2594|267,0:238"/><wd nm="eturn" rd="21,0:1139|27,0:4926,5442|34,0:1280|42,0:1865|53,0:4275|67,0:4279|71,0:2134|72,0:4336,5587,9525|78,0:1162|82,0:2152|83,0:1162|98,0:379|105,0:2187|110,0:816|113,0:2468|124,0:421|125,0:2205|127,0:5432|130,0:1527|132,0:2165|133,0:7853|135,0:580,3057|137,0:292,403|138,0:652|192,0:28326|197,0:602,1619|199,0:673|207,0:2313,24088,24146,24925,25873,25931,27111|223,0:4272|227,0:1145|232,0:4970,5480|239,0:1802|274,0:4337"/><wd nm="eturned" rd="79,0:2730|99,0:1562,1815,5144,5365,6789|111,0:372|112,0:990,1162|116,0:758,930|135,0:2815|138,0:611,10433,10596|192,0:20915|197,0:14015"/><wd nm="eturning" rd="27,0:5371|53,0:4204|67,0:4208|71,0:2063|72,0:4205,5455,9394|82,0:2024|83,0:1034|98,0:308|135,128:47,85,127,3571|223,0:4201|232,0:5409|274,0:4266"/><wd nm="eturns" rd="21,0:3982|23,0:510,643,930|27,0:4861,5514,6442|50,0:481|53,0:3819,4347,5275|64,0:489|67,0:3823,4351,5279|71,0:2206,3134|72,0:3796,4130,5380,9319,9603|73,0:360|77,0:592|82,0:1963|83,0:973|98,0:451,1379|133,0:6873,7514|135,0:2562|139,0:615|192,0:20845|197,0:337,760,1073,1550,4010,5030,5834,8490,13878,14158,14254,14356,14539,14653,18554,18943,19296,19392,19553,20714,22476,22546,23038,23242,23467,23567,23636,23967,24528|199,0:360,1590,1833,1903,2407,2577,2604,3036,3064,3491|202,0:2243,2694,3026|209,0:2788,3230,3371|210,0:4195,6701,7469|211,0:322,727,3343,4055,6941|214,0:8166|220,0:480|223,0:3816,4344,5272|227,0:4046|229,0:512,657,971|232,0:4905,5552,6480|246,0:216|247,0:3878|271,0:495|274,0:3881,4409,5337"/><wd nm="etvalue" rd="155,0:1288"/><wd nm="etween" rd="0,0:3666|12,0:794,1032|13,0:315|14,0:186,464,1679|15,0:249|16,0:2309|24,0:3637|26,0:849,916|30,0:2892|31,0:9290,9362,19129|32,0:3834,4446,4622|33,0:2328,3162|34,0:4109,4721,4897|39,0:2591|41,0:4381,4993,5169|42,0:4389,5006,5182|46,0:7600,10652,11255,11431|51,0:3218|52,0:756,823|54,0:13931,19187|57,0:5819,12252,16280,16358|58,0:3475|60,0:6312,12698,17531,17608|65,0:2799|68,0:7570,7838,7907,15506,20766|69,0:257,865,1143,2362|70,0:4053,4308,4439,4570|72,0:1061,1113,3838,4188,4896,5438,5628,9377,9657,9756|78,0:951|80,0:5943|82,0:404,433|88,0:4288,4419,19062,21229,25116,25729,33009,33099,33251,33359,33516,33692,33814,33908,33961,34080,34166,34265,36539|89,0:3888,19158,20243,24130,24743,31274,31364,31531,31688,31864,31986,32080,32133,32252,32341,32462,32563,32673,32839,35113|90,0:4230,4361,21263,25046,25660,33029,33119,33271,33379,33536,33712,33834,33928,33981,34100,34189,34288,36562|91,0:4209,4340,24593,28480,29093,36573,36663,36815,36923,37080,37256,37378,37472,37525,37644,37733,37832,40105|92,0:4440,4571,19347,21513,25399,26012,33292,33382,33534,33642,33799,33975,34097,34191,34244,34363,34452,34551,36825|93,0:3909,19375,20459,24343,24956,31482,31572,31739,31896,32072,32194,32288,32341,32460,32549,32670,32771,32881,33047,35318|96,0:2587|100,0:2643|112,0:361|116,0:2556|117,0:859,2709|119,0:5867|125,0:904|127,0:2951|128,0:3309|145,0:1793|162,0:563|165,0:3624|167,0:4958,10016,11131,19015,19105|168,0:2814|170,0:87|173,0:7134|174,0:426|177,0:309|179,0:784|182,0:9324,16290,16470,17396,17546,17636|188,0:1144|189,0:3307,3380,3456|190,0:3196|192,0:10538,29852,30107,30238,30369|193,0:217|194,0:537|197,0:1463,11459,12021|206,0:2402|219,0:8160,8429,8501,10544,16680,21944|221,0:3326|222,0:865,932|224,0:8359,8627,8696,10740,16817,22077|230,0:3710|231,0:916,983|234,0:2261|235,0:9370,9444,9516,18048,23302|241,0:427|244,0:3741|245,0:5102,9657,10736,18628,18718|251,0:10257,15833,15936,15994,16104|252,0:4084|255,0:13054,17899,18014|259,0:5806,10647,10735,10820,10878,10988|261,0:1462,2366,2837|263,0:1187,4095,4218|264,0:819,1391|265,0:3098|266,0:966,1556,1822,2184|272,0:2778|275,0:7866,7940,15655,20919"/></pk>