<?xml version="1.0" encoding="UTF-8" standalone="no"?>
<pk><wd nm="ltaneous" rd="168,0:3126|260,0:2782"/><wd nm="ltanimation" rd="31,0:3255|54,0:1939|57,0:2725|60,0:2692|68,0:1920|88,0:6035|89,0:5484|90,0:5977|91,0:5956|92,0:6187|93,0:5487|167,0:2343|182,0:7290|219,0:2516|224,0:2689|235,0:3174|245,0:2485|251,0:2482|255,0:3749|259,0:2136|275,0:1922"/><wd nm="ltant" rd="147,0:4809|152,0:3061,6904|213,0:5685,7026|263,0:2277"/><wd nm="lted" rd="16,0:1875|71,0:1709|95,0:2999|146,0:12315"/><wd nm="lter" rd="241,0:2387|261,0:1546|262,0:473"/><wd nm="ltered" rd="163,0:297|164,0:373"/><wd nm="ltering" rd="0,0:4334|162,0:3157|166,0:308"/><wd nm="lternate" rd="74,0:1837|88,0:4269,24898,25081,25793,25870,25957,26559,26631,26706|89,0:3869,23912,24095,24807,24884,24971|90,0:4211,24828,25011,25724,25801,25888,26490,26562,26637|91,0:4190,28262,28445,29157,29234,29321,29923,29995,30070|92,0:4421,25181,25364,26076,26153,26240,26842,26914,26989|93,0:3890,24125,24308,25020,25097,25184|131,0:3103,3259|146,0:9867|246,0:2449|251,0:9518|253,0:802|255,0:12315|259,0:5068"/><wd nm="lternatebandcolor" rd="131,0:3195"/><wd nm="lternatebandcolors" rd="131,0:3303"/><wd nm="lternatecolorbands" rd="131,0:3048"/><wd nm="lternatehgridalpha" rd="88,0:25899|89,0:1084,1842,24913|90,0:25830|91,0:29263|92,0:26182|93,0:1125,1883,25126"/><wd nm="lternatehgridcolor" rd="88,0:1341,2205,25743,25830|89,0:1223,1248,1995,2022,24757,24844|90,0:1341,2179,25674,25761|91,0:29107,29194|92,0:1398,2322,26026,26113|93,0:1264,1289,2036,2063,24970,25057"/><wd nm="lternatevgridalpha" rd="88,0:26665|90,0:26596|91,0:30029|92,0:26948"/><wd nm="lternatevgridcolor" rd="88,0:26509,26594|90,0:26440,26525|91,0:29873,29958|92,0:26792,26877"/><wd nm="lternative" rd="133,0:2755"/><wd nm="lters" rd="164,0:596|261,0:1650"/><wd nm="ltert" rd="271,0:1848"/><wd nm="ltexportfilename" rd="115,0:9701|131,0:611,933,1115"/><wd nm="ltexportformat" rd="115,0:10062|131,0:907,1353"/><wd nm="ltext" rd="1,0:996,2805,3338|4,0:198,264,328,417,483,547|20,0:2366,2421,2657,2734,2853,2931|27,0:3877,3932,4501,4556|30,0:2259,3469,3517|31,0:25419,25724|37,0:10542|46,0:5324|74,0:3577|88,0:36095,41030|89,0:34669,38138|90,0:36118,41803|91,0:39661,45519|92,0:36381,41316|93,0:34875,38341|150,0:4755|167,0:20353|175,0:2512,2600,4064,4148|179,0:5382,5775,5807|182,0:25817,32483|197,0:9440|225,0:1751,1836,2117,2185,2243,2309|232,0:3927,3969,4562,4600|234,0:1886,2788,2836|235,0:25011,26232|245,0:19975|246,0:4189"/><wd nm="lthough" rd="94,0:4334,7358|140,0:3039|143,0:635|146,0:402,2129,9759"/><wd nm="lti" rd="9,0:5,44,105,215,540,571|44,0:1052,1081|74,0:1258|88,0:29327,29693,35218,35700,36512,40185,40296,41235,41463|89,0:27593,27958,33792,34274,35086,37293,37404,38343,38572|90,0:29348,29713,35241,35723,36535,40958,41069,42008,42237|91,0:32891,33257,38785,39267,40078,44674,44785,45724,45953|92,0:29610,29976,35504,35986,36798,40471,40582,41521,41750|93,0:27802,28168,33999,34480,35291,37496,37607,38546,38775|94,0:1857,2022,7317,7456,7731,8602,8767|96,0:1155,2278|125,0:95|174,0:300|176,0:11,34|208,0:1059|246,0:1868"/><wd nm="lti-lingual" rd="9,128:4362"/><wd nm="lti-tasked" rd="176,128:9358"/><wd nm="ltilingual" rd="101,0:1356|102,0:2923|103,0:6572|107,0:2737|108,0:4300|109,0:4221"/><wd nm="ltime" rd="72,0:473,534|79,0:3887|201,0:727"/><wd nm="ltimearea" rd="88,0:88|186,0:662|189,0:2328"/><wd nm="ltimecolumn" rd="89,0:92|186,0:707|189,0:2373"/><wd nm="ltimecolumn1" rd="89,0:1302,2078|93,0:1343,2119"/><wd nm="ltimedata" rd="53,0:2758,3306,3687,3758,3804|67,0:2762,3310,3691,3762,3808|223,0:2755,3303,3684,3755,3801|274,0:2768,3326,3749,3820,3866"/><wd nm="ltimedyline1" rd="91,0:1032,1837"/><wd nm="ltimeline" rd="78,0:1304|79,0:5835|90,0:88|96,0:3486,4269,4376|186,0:752|189,0:2418"/><wd nm="ltimeline1" rd="88,0:1201,2049|90,0:1201,2031"/><wd nm="ltimelinedy" rd="91,0:100|186,0:920|189,0:2586"/><wd nm="ltimestackedarea" rd="92,0:102|186,0:802|189,0:2468"/><wd nm="ltimestackedcolumn" rd="93,0:107|186,0:861|189,0:2527"/><wd nm="ltimestarea1" rd="92,0:1256,2164"/><wd nm="ltimeupdatecomplete" rd="21,0:4765,4810,4957|23,0:3783|79,0:1286,1331,1477|192,0:18653,18698,18845|196,0:8620|198,0:3563|220,0:2569,2614,2760|227,0:4853,4898,5045|229,0:3765,3810,3956"/><wd nm="ltimeupdateerror" rd="21,0:4790,5165,5373|23,0:3808|79,0:1311,1667,1877|192,0:18678,19057,19265|196,0:8989|198,0:3648|220,0:2594,2953,3163|227,0:4878,5253,5461|229,0:3790,4164,4374"/><wd nm="ltimevalue" rd="72,0:1484,1681,1899,2117,2594|75,0:563,1177,1408,2035|80,0:2099,2706,3329|82,0:717,950,1176,1429|87,0:926,1200,1418,1722|88,0:1154,2000,4706,4767,12957|89,0:1378,2164,4155,4216,12972|90,0:1154,1983,4648,4709,13409|91,0:1145,1478,1957,2299,4627,4688,14523|92,0:1209,2115,4858,4919,13297|93,0:1419,2205,4172,4233,13255|96,0:1299,1607,1836"/><wd nm="ltimevaluefont" rd="88,0:28941|89,0:27207|90,0:28962|91,0:32505|92,0:29224|93,0:27417"/><wd nm="ltimevaluefontcolor" rd="88,0:29167|89,0:27433|90,0:29188|91,0:32731|92,0:29450|93,0:27643"/><wd nm="ltimevaluefontsize" rd="88,0:29053|89,0:27319|90,0:29074|91,0:32617|92,0:29336|93,0:27529"/><wd nm="ltimevaluepadding" rd="70,0:4626,4688,4723,4986|88,0:34213|89,0:32787|90,0:34236|91,0:37780|92,0:34499|93,0:32995|192,0:29348,30425,30486,30521"/><wd nm="ltimevaluesep" rd="88,0:13088|89,0:13103|90,0:13540|91,0:14654|92,0:13428|93,0:13386"/><wd nm="lting" rd="18,0:2127|168,0:1401|225,0:4128"/><wd nm="ltip" rd="4,128:0,31,636,908|22,0:173,1800,1857,1928|28,0:3148,3156|30,0:2293,3424|31,0:2678,22869,22918,23034,23072,23138,23192|37,0:2755,4263|40,0:3407,4469|54,0:327,17657,17706,17822,17860,17932,17986|57,0:331,2262,2270,15235,15285,15401,15439,15505,15559|60,0:328,2231,2239,16428,16477,16593,16631,16697,16751|68,0:291,19236,19285,19401,19439,19511,19565|70,0:2697|88,0:499,5481,5489,20116,31709,31759,31875,31913,31929,32018,32074,32125,32236,36257,36294,38890,41090,41169|89,0:499,4930,4938,29974,30024,30140,30178,30194,30283,30339,30390,30501,34831,34868,38198,38277|90,0:499,5423,5431,20150,31729,31779,31895,31933,31949,32038,32094,32145,32256,36280,36317,39309,41863,41942|91,0:513,5402,5410,23480,35273,35323,35439,35477,35493,35582,35638,35689,35800,39823,39860,43025,45579,45658|92,0:520,5633,5641,8434,8510,20400,31992,32042,32158,32196,32212,32301,32357,32408,32519,36543,36580,39176,41376,41455|93,0:521,4937,4945,8143,8219,30184,30233,30349,30387,30403,30492,30548,30599,30710,35037,35074,38401,38480|96,0:1348|100,0:1632,1640,1884,3340,3378,3447,3498|165,0:2948|167,0:335,1881,1889,17716,17765,17881,17919,17935,17997,18081,18132,18243,20413,20492|177,0:2518,2572|179,0:5511,5576,5614,5641|180,0:4674|182,0:232,4364,4372,14358,14407,14523,14561,14627,14681,14689,14763|195,0:2010,4952,5019|200,0:3323|219,0:385,20412,20462,20578,20616,20688,20742|224,0:382,20547,20596,20712,20750,20822,20876|234,0:1920,2743|235,0:396,2604,2612,21778,21827,21943,21981,22047,22101,26266|244,0:3071|245,0:339,2021,2029,17327,17377,17493,17531,17547,17609,17693,17744,17855,20035,20114|251,0:380,2019,2027,14726,14776,14892,14930,14996,15050|255,0:386,10673,16786,16836,16952,16990,17062,17116|259,0:329,9536,9585,9701,9739,9811,9865|265,0:5919,5927|275,0:302,19387,19437,19553,19591,19663,19717"/><wd nm="ltipbgcolor" rd="31,0:23092|54,0:17886|57,0:15459|60,0:16651|68,0:19465|88,0:1280,2138,32031|89,0:1187,1955,30296|90,0:1280,2115,32051|91,0:35595|92,0:1337,2255,32314|93,0:1228,1996,30505|100,0:3404|167,0:18038|182,0:14581|219,0:20642|224,0:20776|235,0:22001|245,0:17650|251,0:14950|255,0:17016|259,0:9765|275,0:19617"/><wd nm="ltipbordercolor" rd="31,0:23146|54,0:17940|57,0:15513|60,0:16705|68,0:19519|88,0:1301,2161,32082|89,0:1162,1928,30347|90,0:1301,2137,32102|91,0:35646|92,0:1358,2278,32365|93,0:1203,1969,30556|100,0:3455|167,0:18089|182,0:14635|219,0:20696|224,0:20830|235,0:22055|245,0:17701|251,0:15004|255,0:17070|259,0:9819|275,0:19671"/><wd nm="ltiple" rd="1,0:2423,2462,2515|4,128:9,40,96,917|19,0:4697,4730|20,0:295,2485|22,0:1235|24,0:3357|26,0:1566|27,0:491,537,1010,1036|32,0:3556|34,0:3831|41,0:4103|42,0:4111|44,0:1932|46,0:10374|59,0:568|74,0:2089,2143,2455,2733|79,0:1024,3395|82,128:27,51,251,3465,4221|83,128:28,52,460,632,656,3158|84,0:999,1060|88,0:10643,13144,31439,31493|89,0:10505,13159,29704,29758|90,0:11095,13596,31459,31513|91,0:12209,14710,35003,35057|92,0:10983,13484,31722,31776|93,0:10693,13442,29914,29968|103,0:1350,2445|114,0:94|115,0:4309|117,128:56,81,107,421,632,1793,4613,4680,8982|119,0:9394|120,0:286|128,0:6005,6320|133,0:1019,4574|137,0:1136|138,0:11974|150,128:23,60,471,555,1168,5602|152,0:10451|156,0:657|160,128:27,50,823,1249,5071|161,0:3098,3524,10679|169,0:1286|172,0:800|176,0:160,306,1350,5774|177,0:898,1663,1807|180,0:283|187,0:1196|192,0:27355|195,0:441,2037,3441,6568|197,0:4982,5786|198,0:458|200,0:1138,2569,2707|201,0:9570,10107,10244,10298|209,0:2262|210,0:1140|211,0:502,3170,3882,7357|213,0:9649|214,0:4739,9216,9369,9576|225,0:215,1167,1971,1994,2027|226,0:3986,4022|228,0:1173|230,0:3402,3438|231,0:183|232,0:489,541,1014,1040|238,0:656,772|246,0:583,2701,2755,3067,3345,5818,5872,5953,6053,6526,6552,6588|247,0:1519,4232,4348|260,0:1772,1805|265,0:1912,2112,6532,6695,6861,7111|267,0:1022,1053,1577,2211"/><wd nm="ltiplecharts" rd="160,0:407"/><wd nm="ltipleds" rd="79,0:5886"/><wd nm="ltiples" rd="180,0:4826,10694"/><wd nm="ltips" rd="4,0:86,747|31,0:23253|54,0:18047|60,0:16812|68,0:19626|88,0:19762,19835,19918,20707,32297|89,0:30562|90,0:19796,19869,19952,20741,32317|91,0:23127,23200,23283,24071,35861|92,0:20047,20120,20203,20991,32580|93,0:30771|167,0:18304|169,0:4202|175,0:4841|182,0:14825|190,0:1714|200,0:3237|219,0:20803|224,0:20937|235,0:22162|245,0:17916|251,0:15111|255,0:17177|259,0:9926|275,0:19778"/><wd nm="ltipsepchar" rd="88,0:32133|89,0:1208,1978,30398|90,0:32153|91,0:35697|92,0:32416|93,0:1249,2019,30607|167,0:18140|245,0:17752"/><wd nm="ltipshadow" rd="31,0:23200|54,0:17994|60,0:16759|68,0:19573|88,0:32244|89,0:30509|90,0:32264|91,0:35808|92,0:32527|93,0:30718|167,0:18251|182,0:14772|219,0:20750|224,0:20884|235,0:22109|245,0:17863|251,0:15058|255,0:17124|259,0:9873|275,0:19725"/><wd nm="ltitle" rd="115,0:12597|131,0:2943,4193"/><wd nm="ltnumberscale" rd="7,0:3329,4892,5240|8,0:650,898,1196,2569,2901|31,0:16802|54,0:11598|57,0:8281|60,0:8725|68,0:13173|88,0:14977|89,0:14992|90,0:15429|91,0:16543,19935|92,0:15254|93,0:15211|167,0:7528|219,0:14352|224,0:14490|235,0:15721|245,0:7441|251,0:7211|255,0:8372|275,0:13330"/></pk>